collagemaker/__init__.py
collagemaker/main.py
collagemaker_tspspi-0.0.1.dist-info/LICENSE.md
collagemaker_tspspi-0.0.1.dist-info/METADATA
collagemaker_tspspi-0.0.1.dist-info/WHEEL
collagemaker_tspspi-0.0.1.dist-info/entry_points.txt
collagemaker_tspspi-0.0.1.dist-info/top_level.txt
collagemaker_tspspi-0.0.1.dist-info/RECORD
