Metadata-Version: 2.1
Name: collagemaker-tspspi
Version: 0.0.1
Summary: A simple photo collage generator
Home-page: https://github.com/tspspi/pycollagemaker
Author: Thomas Spielauer
Author-email: pypipackages01@tspi.at
Classifier: Programming Language :: Python :: 3
Classifier: License :: OSI Approved :: BSD License
Classifier: Operating System :: OS Independent
Requires-Python: >=3.6
License-File: LICENSE.md
Requires-Dist: pillow>=11.0.0
